viewtif/__init__.py
viewtif/tif_viewer.py
viewtif-0.2.6.dist-info/METADATA
viewtif-0.2.6.dist-info/WHEEL
viewtif-0.2.6.dist-info/entry_points.txt
viewtif-0.2.6.dist-info/licenses/LICENSE
viewtif-0.2.6.dist-info/RECORD
