Metadata-Version: 2.4
Name: viewtif
Version: 0.2.6
Summary: Lightweight GeoTIFF, NetCDF, HDF/HDF5, and Esri File Geodatabase (.gdb) viewer with optional shapefile overlay. NetCDF and cartopy support available via pip install viewtif[netcdf].
Project-URL: Homepage, https://github.com/nkeikon/tifviewer
Project-URL: Source, https://github.com/nkeikon/tifviewer
Project-URL: Issues, https://github.com/nkeikon/tifviewer/issues
Author: Keiko Nomura
License: MIT
License-File: LICENSE
Requires-Python: >=3.10
Requires-Dist: click>=8.1
Requires-Dist: matplotlib>=3.7
Requires-Dist: numpy>=1.23
Requires-Dist: pyside6>=6.5
Requires-Dist: rasterio>=1.3
Provides-Extra: geo
Requires-Dist: geopandas>=0.13; extra == 'geo'
Requires-Dist: shapely>=2.0; extra == 'geo'
Provides-Extra: netcdf
Requires-Dist: cartopy>=0.22; extra == 'netcdf'
Requires-Dist: netcdf4>=1.6; extra == 'netcdf'
Requires-Dist: pandas>=2.0; extra == 'netcdf'
Requires-Dist: xarray>=2023.1; extra == 'netcdf'
